pyspice/__init__.py
pyspice/dialogs.py
pyspice/editor_widget.py
pyspice/file_browser.py
pyspice/highlighter.py
pyspice/line_number_text_edit.py
pyspice/magic_scrollbar.py
pyspice/main.py
pyspice/resources.py
pyspice/spice_console.py
pyspice/spice_magic_editor.py
pyspice/splitter.py
pyspice/term.py
pyspice/textract.py
pyspice/utils.py
spiceditor/__init__.py
spiceditor/dialogs.py
spiceditor/editor_widget.py
spiceditor/file_browser.py
spiceditor/highlighter.py
spiceditor/line_number_text_edit.py
spiceditor/magic_scrollbar.py
spiceditor/main.py
spiceditor/resources.py
spiceditor/spice_console.py
spiceditor/spice_magic_editor.py
spiceditor/splitter.py
spiceditor/term.py
spiceditor/textract.py
spiceditor/utils.py
spyce/__init__.py
spyce/dialogs.py
spyce/editor_widget.py
spyce/file_browser.py
spyce/highlighter.py
spyce/line_number_text_edit.py
spyce/magic_scrollbar.py
spyce/main.py
spyce/resources.py
spyce/spice_console.py
spyce/spice_magic_editor.py
spyce/splitter.py
spyce/term.py
spyce/textract.py
spyce/utils.py
spiceditor-0.0.4.dist-info/LICENSE
spiceditor-0.0.4.dist-info/METADATA
spiceditor-0.0.4.dist-info/WHEEL
spiceditor-0.0.4.dist-info/entry_points.txt
spiceditor-0.0.4.dist-info/top_level.txt
spiceditor-0.0.4.dist-info/RECORD
