Metadata-Version: 2.2
Name: spiceditor
Version: 0.0.4
Summary: Spice is a Python IDE for students
Home-page: https://github.com/dantard/coder
Author: Danilo Tardioli
Author-email: dantard@unizar.es
Classifier: Programming Language :: Python :: 3
Classifier: License :: OSI Approved :: MIT License
Classifier: Operating System :: OS Independent
Requires-Python: >=3.10
License-File: LICENSE
Requires-Dist: pyqt5
Requires-Dist: pymupdf>=1.18.17
Requires-Dist: autopep8
Requires-Dist: scipy
Requires-Dist: qtconsole
Requires-Dist: termqt
Requires-Dist: easyconfig2
Dynamic: author
Dynamic: author-email
Dynamic: classifier
Dynamic: description
Dynamic: description-content-type
Dynamic: home-page
Dynamic: requires-dist
Dynamic: requires-python
Dynamic: summary
